df_qc_tools/__init__.py
df_qc_tools/config.py
df_qc_tools/qc.py
df_qc_tools-0.0.16.dist-info/METADATA
df_qc_tools-0.0.16.dist-info/WHEEL
df_qc_tools-0.0.16.dist-info/licenses/LICENSE
df_qc_tools-0.0.16.dist-info/RECORD
