Metadata-Version: 2.4
Name: df-qc-tools
Version: 0.0.16
Summary: Package for easy datarequests from sensortings
Project-URL: Homepage, https://github.com/nvdsteen/pandassta
Project-URL: Issues, https://github.com/nvdsteen/pandassta/issues
Author: nvds
License-File: LICENSE
Classifier: License :: OSI Approved :: GNU Affero General Public License v3
Classifier: Operating System :: OS Independent
Classifier: Programming Language :: Python :: 3
Requires-Python: >=3.11
Requires-Dist: geopandas==1.0.1
Requires-Dist: geopy==2.4.1
Requires-Dist: hydra-core==1.3.2
Requires-Dist: netcdf4==1.7.2
Requires-Dist: numpy==2.2.3
Requires-Dist: omegaconf==2.3.0
Requires-Dist: pandas==2.2.3
Requires-Dist: pandassta>=0.0.18
Requires-Dist: pytest==8.3.5
Requires-Dist: scipy==1.15.2
Requires-Dist: searegion-detection>=0.0.4
Requires-Dist: tqdm==4.67.1
Requires-Dist: xarray==2025.1.2
